{
  "HALProvider": {
    "Other Devices": {
      "Talon FX (v6)[14]": {
        "header": {
          "open": true
        }
      },
      "Talon FX (v6)[14]/Rotor Sensor": {
        "header": {
          "open": true
        }
      }
    }
  },
  "NTProvider": {
    "types": {
      "/FMSInfo": "FMSInfo"
    }
  },
  "NetworkTables": {
    "Retained Values": {
      "open": false
    },
    "Robot": {
      "open": true
    },
    "RobotContainer": {
      "open": true,
      "superstructure": {
        "open": true,
        "shooter": {
          "open": true
        }
      }
    },
    "combined": true,
    "transitory": {
      "Robot": {
        "open": true
      },
      "RobotContainer": {
        "open": true,
        "superstructure": {
          "open": true
        }
      },
      "Shuffleboard": {
        ".recording": {
          "open": true
        }
      }
    }
  },
  "NetworkTables Info": {
    "Clients": {
      "open": true
    },
    "Server": {
      "Subscribers": {
        "open": true
      },
      "open": true
    },
    "visible": true
  },
  "Plot": {
    "Plot <0>": {
      "plots": [
        {
          "backgroundColor": [
            0.0,
            0.0,
            0.0,
            0.8500000238418579
          ],
          "height": 367,
          "series": [
            {
              "color": [
                0.2980392277240753,
                0.44705885648727417,
                0.6901960968971252,
                1.0
              ],
              "id": "CANEncoder:Talon FX (v6)[14]/Rotor Sensor-velocity"
            },
            {
              "color": [
                0.3333333432674408,
                0.658823549747467,
                0.4078431725502014,
                1.0
              ],
              "id": "NT:/RobotContainer/superstructure/shooter/getShooterErrorRPS"
            }
          ]
        }
      ]
    },
    "Plot <1>": {
      "plots": [
        {
          "backgroundColor": [
            0.0,
            0.0,
            0.0,
            0.8500000238418579
          ],
          "height": 366
        }
      ]
    }
  }
}
